{
  "trigger": true,
  "modules": [
    "verification-link"
  ],
  "parentResource": "gibgymdemo1",
  "functionName": "gibgymdemo1CustomMessage",
  "resourceName": "gibgymdemo1CustomMessage",
  "parentStack": "auth",
  "triggerEnvs": [
    {
      "key": "RESOURCENAME",
      "value": "resourceName"
    }
  ],
  "triggerDir": "C:\\Users\\kkr03\\AppData\\Roaming\\npm\\node_modules\\@aws-amplify\\cli\\node_modules\\amplify-category-auth\\provider-utils\\awscloudformation\\triggers\\CustomMessage",
  "triggerTemplate": "CustomMessage.json.ejs",
  "roleName": "gibgymdemo1CustomMessage",
  "skipEdit": true,
  "REDIRECTURL": "",
  "EMAILSUBJECT": "",
  "EMAILMESSAGE": "GIBGYM Process Succeeded ",
  "RESOURCENAME": "resourceName"
}